quotefix.py
setup.cfg
setup.py
quotefix.egg-info/PKG-INFO
quotefix.egg-info/SOURCES.txt
quotefix.egg-info/dependency_links.txt
quotefix.egg-info/top_level.txt