Metadata-Version: 1.0
Name: quotefix
Version: 1.0.1
Summary: Insert matching punctuation in strings
Home-page: https://github.com/pteichman/quotefix
Author: Peter Teichman
Author-email: peter@teichman.org
License: MIT
Platform: UNKNOWN
